payment_date_time/__init__.py
payment_date_time/date_time_util.py
payment_date_time-0.1.dist-info/licenses/LICENSE
payment_date_time-0.1.dist-info/METADATA
payment_date_time-0.1.dist-info/WHEEL
payment_date_time-0.1.dist-info/top_level.txt
payment_date_time-0.1.dist-info/RECORD
