Metadata-Version: 2.4
Name: payment_date_time
Version: 0.1
Summary: This is a simple Python package for showing payment current date and time.
Home-page: 
Author: Siddharth Manik
Author-email:  x23289678@student.ncirl.ie
License: MIT
Keywords: payment_date_time
Classifier: Intended Audience :: Education
Classifier: Operating System :: Microsoft :: Windows :: Windows 10
Classifier: Programming Language :: Python :: 3
Requires-Python: >=3.6
License-File: LICENSE
Dynamic: author
Dynamic: author-email
Dynamic: classifier
Dynamic: description
Dynamic: keywords
Dynamic: license
Dynamic: license-file
Dynamic: requires-python
Dynamic: summary
